contextM/__init__.py
ContextM-1.0.0.dist-info/LICENSE
ContextM-1.0.0.dist-info/METADATA
ContextM-1.0.0.dist-info/WHEEL
ContextM-1.0.0.dist-info/top_level.txt
ContextM-1.0.0.dist-info/RECORD
