Metadata-Version: 2.1
Name: ContextM
Version: 1.0.0
Summary: Helps in the process of creating a context manager
Home-page: https://www.beyonce.com
Author: hunterg
Author-email: redissuslolol@gmail.com
License: UNKNOWN
Platform: UNKNOWN
Classifier: Programming Language :: Python :: 3
Classifier: License :: OSI Approved :: MIT License
Classifier: Operating System :: OS Independent
Requires-Python: >=3.6
Requires-Dist: decorate-all-methods
